[
  {
    "id": "evt_GJ_surat_20260114_001",
    "stateId": "GJ",
    "districtId": "surat",
    "regionId": "surat-city",
    "category": "safety",
    "impactScale": "POINT",
    "title": "Family Dies in Flyover Fall",
    "summary": "A family of three died after their scooter hit a railing on the Chandrashekhar Azad flyover and plunged 70 feet in Adajan.",
    "timestamp": "2026-01-14T16:00:00Z",
    "expiresAt": null,
    "geoPoint": {
      "lat": 21.1965,
      "lng": 72.7989
    },
    "location": {
      "block": "Adajan (Chandrashekhar Azad Flyover)"
    },
    "source": "The Week",
    "verified": true,
    "meta": {
      "fatalities": 3,
      "incidentType": "Road Accident"
    },
    "translations": {
      "gu": {
        "title": "ફ્લાયઓવર પરથી પટકાતા પરિવારનું મોત",
        "summary": "અડાજણમાં ચંદ્રશેખર આઝાદ ફ્લાયઓવરની રેલિંગ સાથે સ્કૂટર અથડાતા અને 70 ફૂટ નીચે પટકાતા પરિવારના ત્રણ સભ્યોના મોત થયા છે।"
      },
      "hi": {
        "title": "फ्लाईओवर से गिरकर परिवार की मौत",
        "summary": "अडाजण में चंद्रशेखर आज़ाद फ्लाईओवर की रेलिंग से स्कूटर टकराने और 70 फीट नीचे गिरने से एक ही परिवार के तीन सदस्यों की मौत हो गई।"
      },
      "mr": {
        "title": "फ्लाईओव्हरवरून पडून कुटुंबाचा मृत्यू",
        "summary": "अडाजण येथील चंद्रशेखर आझाद फ्लाईओव्हरच्या रेलिंगला स्कूटर धडकून ७० फूट खाली कोसळल्याने एकाच कुटुंबातील तिघांचा मृत्यू झाला।"
      }
    }
  },
  {
    "id": "evt_GJ_surat_20260301_002",
    "stateId": "GJ",
    "districtId": "surat",
    "regionId": "chorasi",
    "category": "safety",
    "title": "Workers Arrested After Plant Unrest",
    "summary": "Police arrested 40 workers at the AM/NS plant following an outbreak of unrest in Hazira.",
    "timestamp": "2026-03-01T08:30:00Z",
    "expiresAt": null,
    "geoPoint": {
      "lat": 21.1685,
      "lng": 72.6567
    },
    "location": {
      "block": "Hazira (AM/NS Plant)"
    },
    "source": "Times of India",
    "verified": true,
    "meta": {
      "arrests": 40,
      "charges": "Attempted Murder"
    },
    "translations": {
      "gu": {
        "title": "પ્લાન્ટમાં અશાંતિ બાદ કામદારોની ધરપકડ",
        "summary": "હજીરામાં AM/NS પ્લાન્ટમાં અશાંતિ ફાટી નીકળ્યા બાદ પોલીસે 40 કામદારોની ધરપકડ કરી હતી."
      },
      "hi": {
        "title": "प्लांट में अशांति के बाद मजदूर गिरफ्तार",
        "summary": "हजीरा स्थित AM/NS प्लांट में अशांति फैलने के बाद पुलिस ने 40 मजदूरों को गिरफ्तार किया।"
      },
      "mr": {
        "title": "प्लांटमध्ये अशांतीनंतर कामगारांना अटक",
        "summary": "हजीरा येथील AM/NS प्लांटमध्ये झालेल्या अशांतीनंतर पोलिसांनी 40 कामगारांना अटक केली।"
      }
    }
  },
  {
    "id": "evt_GJ_surat_20260301_003",
    "stateId": "GJ",
    "districtId": "surat",
    "regionId": null,
    "category": "health",
    "impactScale": "LOCAL",
    "title": "HPV Vaccine Drive Launch Planned",
    "summary": "A statewide vaccination campaign against Human Papillomavirus for teenage girls is set to begin full-scale operations.",
    "timestamp": "2026-03-01T10:00:00Z",
    "expiresAt": "2026-04-01T10:00:00Z",
    "location": {
      "block": "Surat District Health Centers"
    },
    "source": "Indian Express",
    "verified": true,
    "meta": {
      "targetGroup": "Teenage girls",
      "vaccineType": "HPV",
      "clusterPoints": [
        {
          "lat": 21.1702,
          "lng": 72.8311
        },
        {
          "lat": 21.1965,
          "lng": 72.7989
        },
        {
          "lat": 21.1411,
          "lng": 72.7758
        }
      ]
    }
  },
  {
    "id": "evt_GJ_surat_20260223_001",
    "stateId": "GJ",
    "districtId": "surat",
    "regionId": "surat-city",
    "category": "safety",
    "title": "Diamond Traders Booked for Fraud",
    "summary": "The Gajera brothers were booked in a massive Rs 1,928 crore cheating and forgery case involving funds from Ring Road textile markets.",
    "timestamp": "2026-02-23T14:15:00Z",
    "expiresAt": null,
    "geoPoint": {
      "lat": 21.1901,
      "lng": 72.8433
    },
    "location": {
      "block": "Ring Road Textile Market"
    },
    "source": "DeshGujarat",
    "verified": true,
    "meta": {
      "fraudAmount": 19280000000,
      "accused": "Gajera Brothers"
    }
  },
  {
    "id": "evt_GJ_surat_20260301_006",
    "stateId": "GJ",
    "districtId": "surat",
    "regionId": "surat-city",
    "category": "emergency",
    "title": "Market Fire Rescues Successful",
    "summary": "A fire broke out at a city market, leading to the rescue of four individuals trapped in a lift.",
    "timestamp": "2026-03-01T11:20:00Z",
    "expiresAt": null,
    "geoPoint": {
      "lat": 21.185,
      "lng": 72.825
    },
    "location": {
      "block": "Main City Market"
    },
    "source": "Times of India",
    "verified": true,
    "meta": {
      "rescued": 4,
      "severity": "Moderate"
    }
  },
  {
    "id": "evt_GJ_surat_20260108_001",
    "stateId": "GJ",
    "districtId": "surat",
    "regionId": "surat-city",
    "category": "health",
    "title": "Waterborne Disease Counter-Drive",
    "summary": "The SMC Health Department intensified monitoring of diseases in the Udhna and Limbayat zones.",
    "timestamp": "2026-01-08T10:00:00Z",
    "expiresAt": "2026-02-08T10:00:00Z",
    "geoPoint": {
      "lat": 21.1743,
      "lng": 72.8422
    },
    "location": {
      "block": "Udhna and Limbayat Zones"
    },
    "source": "Times of India",
    "verified": true,
    "meta": {
      "caseType": "Typhoid",
      "monitoringDaily": true
    }
  },
  {
    "id": "evt_GJ_surat_20260114_002",
    "stateId": "GJ",
    "districtId": "surat",
    "regionId": null,
    "category": "mobility",
    "title": "BRTS Shutdown for Uttarayan",
    "summary": "All BRTS bus services were suspended to prevent kite string accidents across multiple city corridors.",
    "timestamp": "2026-01-14T06:00:00Z",
    "expiresAt": "2026-01-14T22:00:00Z",
    "geoPoint": {
      "lat": 21.1702,
      "lng": 72.8311
    },
    "location": {
      "block": "BRTS Corridors"
    },
    "source": "DeshGujarat",
    "verified": true,
    "meta": {
      "serviceStatus": "Suspended",
      "reason": "Public Safety"
    }
  },
  {
    "id": "evt_HR_gurugram_20260131_001",
    "stateId": "HR",
    "districtId": "gurugram",
    "regionId": "gurugram-sadar",
    "category": "health",
    "title": "ARI Spike — Winter Pollution Impact",
    "summary": "2,293 acute respiratory illness emergencies recorded. 358 case increase over previous winter due to poor AQI.",
    "timestamp": "2026-01-31T18:00:00Z",
    "expiresAt": "2026-03-15T18:00:00Z",
    "geoPoint": {
      "lat": 28.4595,
      "lng": 77.0266
    },
    "location": {
      "block": "Gurugram Sadar — Civil Hospital, Medanta, Paras"
    },
    "source": "Gurugram Health Dept / HT",
    "verified": true,
    "verifiedAt": "2026-01-31T23:23:00Z",
    "meta": {
      "caseCount": 2293,
      "sentinelSites": [
        "Medanta",
        "Paras",
        "Civil Hospital Sector 10"
      ],
      "pollutantFocus": "PM2.5 / PM10"
    }
  },
  {
    "id": "evt_HR_gurugram_20260203_001",
    "stateId": "HR",
    "districtId": "gurugram",
    "regionId": "gurugram-sadar",
    "category": "infrastructure",
    "title": "Service Road Repairs — Sector 30/31",
    "summary": "GMDA tenders floated for service lane upgrades and footpath repairs to reduce highway congestion.",
    "timestamp": "2026-02-03T07:12:00Z",
    "expiresAt": "2026-08-01T18:00:00Z",
    "geoPoint": {
      "lat": 28.455,
      "lng": 77.058
    },
    "location": {
      "block": "Sector 30-31, Gurugram"
    },
    "source": "GMDA / Hindustan Times",
    "verified": true,
    "verifiedAt": "2026-02-03T09:00:00Z",
    "meta": {
      "projectLengthKm": 7.5,
      "authority": "GMDA",
      "scope": [
        "Service lane repair",
        "Encroachment removal"
      ]
    }
  },
  {
    "id": "evt_HR_gurugram_20260218_001",
    "stateId": "HR",
    "districtId": "gurugram",
    "regionId": "gurugram-sadar",
    "category": "mobility",
    "title": "Fatal Crash — KMP Expressway",
    "summary": "Dumper truck collision with tourist vehicle resulting in 2 fatalities. Significant traffic disruption reported.",
    "timestamp": "2026-02-18T08:07:00Z",
    "expiresAt": "2026-02-19T12:00:00Z",
    "geoPoint": {
      "lat": 28.3245,
      "lng": 76.8521
    },
    "location": {
      "block": "KMP Expressway, Gurugram-Rewari stretch"
    },
    "source": "Gurugram Traffic Police",
    "verified": true,
    "verifiedAt": "2026-02-18T09:30:00Z",
    "meta": {
      "vehicleTypes": [
        "Dumper",
        "Sedan"
      ],
      "fatalities": 2,
      "highway": "KMP Expressway"
    }
  },
  {
    "id": "evt_HR_gurugram_20260222_001",
    "stateId": "HR",
    "districtId": "gurugram",
    "regionId": "badshahpur",
    "category": "safety",
    "title": "Serious Assault — Badshahpur Police Area",
    "summary": "19-year-old student assaulted. Accused arrested under serious criminal charges. Investigation active.",
    "timestamp": "2026-02-22T13:30:00Z",
    "expiresAt": null,
    "geoPoint": {
      "lat": 28.3962,
      "lng": 77.0543
    },
    "location": {
      "block": "Badshahpur, Gurugram"
    },
    "source": "Badshahpur Police / ANI",
    "verified": true,
    "verifiedAt": "2026-02-22T15:00:00Z",
    "meta": {
      "arrestStatus": "Accused in custody",
      "incidentType": "Criminal Assault",
      "station": "Badshahpur"
    }
  },
  {
    "id": "evt_HR_gurugram_20251214_001",
    "stateId": "HR",
    "districtId": "gurugram",
    "regionId": null,
    "category": "weather",
    "impactScale": "WIDE",
    "title": "Dense Fog — Massive Pile-up Advisory",
    "summary": "Visibility < 50m causing multiple vehicle collisions across Haryana highways, including Gurugram sectors.",
    "timestamp": "2025-12-14T12:34:00Z",
    "expiresAt": "2025-12-16T12:00:00Z",
    "geoPoint": {
      "lat": 28.4595,
      "lng": 77.0266
    },
    "location": {
      "block": "District-wide highway corridors"
    },
    "source": "IMD / Local News",
    "verified": true,
    "verifiedAt": "2025-12-14T13:00:00Z",
    "meta": {
      "visibilityMeters": 50,
      "alertLevel": "orange",
      "impact": "Highway pile-ups"
    }
  },
  {
    "id": "evt_MH_pune_20260301_001",
    "stateId": "MH",
    "districtId": "pune",
    "regionId": "haveli",
    "category": "emergency",
    "title": "Dump Site Fire Hospitalizes Five",
    "summary": "A massive fire at a garbage dump on the Mula-Mutha river bed led to the hospitalization of five students with breathing issues in Loni Kalbhor.",
    "timestamp": "2026-03-01T01:36:00Z",
    "expiresAt": null,
    "geoPoint": {
      "lat": 18.4875,
      "lng": 74.0194
    },
    "location": {
      "block": "Loni Kalbhor"
    },
    "source": "The Times of India",
    "verified": true,
    "meta": {
      "hospitalizedCount": 5,
      "incidentType": "Fire",
      "radiusMetres": 1500
    }
  },
  {
    "id": "evt_MH_pune_20260301_002",
    "stateId": "MH",
    "districtId": "pune",
    "regionId": null,
    "category": "safety",
    "title": "Propylene Tanker Overturns on Expressway",
    "summary": "An inflammable gas tanker overturned near Khopoli, resulting in a 33-hour traffic halt on the Mumbai-Pune Expressway.",
    "timestamp": "2026-03-01T08:00:00Z",
    "expiresAt": "2026-03-02T17:00:00Z",
    "geoPoint": {
      "lat": 18.7881,
      "lng": 73.3444
    },
    "location": {
      "block": "Khopoli Stretch, Expressway"
    },
    "source": "Hindustan Times",
    "verified": true,
    "meta": {
      "disruptionDurationHours": 33,
      "chemical": "Propylene"
    }
  },
  {
    "id": "evt_MH_pune_20260225_001",
    "stateId": "MH",
    "districtId": "pune",
    "regionId": "pune-city",
    "category": "infrastructure",
    "title": "Construction Stop Notices Issued",
    "summary": "PMC issued stop-work notices to 220 construction sites for failing to implement air pollution control measures across city areas.",
    "timestamp": "2026-02-25T05:04:00Z",
    "expiresAt": null,
    "geoPoint": {
      "lat": 18.5204,
      "lng": 73.8567
    },
    "location": {
      "block": "Pune City (Various)"
    },
    "source": "The Indian Express",
    "verified": true,
    "meta": {
      "noticesIssued": 220,
      "complianceRate": "87%"
    }
  },
  {
    "id": "evt_MH_pune_20260224_001",
    "stateId": "MH",
    "districtId": "pune",
    "regionId": "haveli",
    "category": "safety",
    "title": "Fatal Crash Near Katraj Tunnel",
    "summary": "A truck driver died and several passengers were injured after a truck carrying iron pipes collided with a bus at Katraj Ghat.",
    "timestamp": "2026-02-23T22:30:00Z",
    "expiresAt": null,
    "geoPoint": {
      "lat": 18.4312,
      "lng": 73.8561
    },
    "location": {
      "block": "Katraj Ghat (Jambhulwadi)"
    },
    "source": "The Bridge Chronicle",
    "verified": true,
    "meta": {
      "fatalities": 1,
      "injured": 5
    }
  },
  {
    "id": "evt_MH_pune_20260223_001",
    "stateId": "MH",
    "districtId": "pune",
    "regionId": "pune-city",
    "category": "weather",
    "title": "Second Highest February Minimum Temp",
    "summary": "Shivajinagar recorded a minimum temperature of 19.2°C, the second-highest for February since 2015.",
    "timestamp": "2026-02-22T23:08:00Z",
    "expiresAt": "2026-02-28T18:00:00Z",
    "geoPoint": {
      "lat": 18.5312,
      "lng": 73.8445
    },
    "location": {
      "block": "Shivajinagar"
    },
    "source": "Hindustan Times",
    "verified": true,
    "meta": {
      "temperatureCelsius": 19.2,
      "departureFromNormal": 5.8
    }
  },
  {
    "id": "evt_MH_pune_20260222_001",
    "stateId": "MH",
    "districtId": "pune",
    "regionId": null,
    "category": "health",
    "title": "High Chikungunya Infection Rates",
    "summary": "Pune district logged the highest chikungunya infections and second-highest dengue cases in Maharashtra for the 2025 season.",
    "timestamp": "2026-02-22T08:00:00Z",
    "expiresAt": null,
    "geoPoint": {
      "lat": 18.5204,
      "lng": 73.8567
    },
    "location": {
      "block": "Pune District"
    },
    "source": "The Times of India",
    "verified": true,
    "meta": {
      "chikungunyaCases": 22,
      "dengueCases": 44
    }
  },
  {
    "id": "evt_MH_pune_20260215_001",
    "stateId": "MH",
    "districtId": "pune",
    "regionId": "pune-city",
    "category": "infrastructure",
    "title": "Mula Mutha Riverfront Stretch Opened",
    "summary": "The Pune Municipal Corporation opened a 1.5 km rejuvenated stretch of the riverfront in Yerawada-Kalyani Nagar.",
    "timestamp": "2026-02-15T04:30:00Z",
    "expiresAt": null,
    "geoPoint": {
      "lat": 18.5362,
      "lng": 73.894
    },
    "location": {
      "block": "Yerawada-Kalyani Nagar"
    },
    "source": "Times Property",
    "verified": true,
    "meta": {
      "stretchLengthKm": 1.5
    }
  },
  {
    "id": "evt_MH_pune_20260210_001",
    "stateId": "MH",
    "districtId": "pune",
    "regionId": "pune-city",
    "category": "infrastructure",
    "title": "MHADA Lottery Results Declared",
    "summary": "Results for the Pune MHADA housing lottery were officially declared for thousands of affordable units.",
    "timestamp": "2026-02-10T05:00:00Z",
    "expiresAt": null,
    "geoPoint": {
      "lat": 18.5284,
      "lng": 73.8744
    },
    "location": {
      "block": "MHADA Pune Office"
    },
    "source": "Times Property",
    "verified": true,
    "meta": {
      "event": "Lottery Draw"
    }
  },
  {
    "id": "evt_MH_pune_20260204_001",
    "stateId": "MH",
    "districtId": "pune",
    "regionId": null,
    "category": "mobility",
    "title": "Gas Tanker Overturns Near Tunnel",
    "summary": "A gas tanker overturned near Aadoshi tunnel, causing a 50km traffic jam on the Mumbai-Pune Expressway for 20 hours.",
    "timestamp": "2026-02-04T11:30:00Z",
    "expiresAt": "2026-02-05T08:00:00Z",
    "geoPoint": {
      "lat": 18.7667,
      "lng": 73.3833
    },
    "location": {
      "block": "Aadoshi Tunnel"
    },
    "source": "News18 Marathi",
    "verified": true,
    "meta": {
      "jamLengthKm": 50,
      "blockageHours": 20
    }
  },
  {
    "id": "evt_MH_pune_20260202_001",
    "stateId": "MH",
    "districtId": "pune",
    "regionId": "pune-city",
    "category": "safety",
    "title": "Three Fatalities in Road Accidents",
    "summary": "Three people died in separate road accidents involving a PMPML bus and trucks in Aundh and Nagar Road.",
    "timestamp": "2026-02-02T04:00:00Z",
    "expiresAt": null,
    "geoPoint": {
      "lat": 18.5135,
      "lng": 73.8122
    },
    "location": {
      "block": "Uttamnagar, Aundh, Nagar Road"
    },
    "source": "The Bridge Chronicle",
    "verified": true,
    "meta": {
      "fatalities": 3
    }
  },
  {
    "id": "evt_MH_pune_20260126_001",
    "stateId": "MH",
    "districtId": "pune",
    "regionId": "pune-city",
    "category": "safety",
    "title": "Pune Road Fatalities Surge",
    "summary": "Police data reveals a crisis with 290 road deaths in the past year, primarily affecting pedestrians and bikers in Pune City.",
    "timestamp": "2026-01-26T05:30:00Z",
    "expiresAt": null,
    "geoPoint": {
      "lat": 18.5204,
      "lng": 73.8567
    },
    "location": {
      "block": "Pune City"
    },
    "source": "The Bridge Chronicle",
    "verified": true,
    "meta": {
      "annualFatalities": 290,
      "seriousAccidents": 633
    }
  },
  {
    "id": "evt_MH_pune_20260125_001",
    "stateId": "MH",
    "districtId": "pune",
    "regionId": "daund",
    "category": "mobility",
    "title": "High Speed Train Trials Conducted",
    "summary": "High-speed train trials were successfully conducted on the Daund-Kashti section of the Pune division.",
    "timestamp": "2026-01-25T07:00:00Z",
    "expiresAt": null,
    "geoPoint": {
      "lat": 18.4684,
      "lng": 74.5878
    },
    "location": {
      "block": "Daund-Kashti Section"
    },
    "source": "Times Property",
    "verified": true,
    "meta": {
      "trialType": "High Speed"
    }
  },
  {
    "id": "evt_MH_pune_20260120_001",
    "stateId": "MH",
    "districtId": "pune",
    "regionId": null,
    "category": "infrastructure",
    "title": "Outer Ring Road Work Progresses",
    "summary": "Major groundwork for the Pune Outer Ring Road has been completed in the Sangrun and Davaje segments.",
    "timestamp": "2026-01-20T08:00:00Z",
    "expiresAt": null,
    "geoPoint": {
      "lat": 18.4233,
      "lng": 73.7431
    },
    "location": {
      "block": "Sangrun and Davaje"
    },
    "source": "Times Property",
    "verified": true,
    "meta": {
      "project": "Outer Ring Road",
      "status": "Construction Underway"
    }
  },
  {
    "id": "evt_MH_pune_20260119_001",
    "stateId": "MH",
    "districtId": "pune",
    "regionId": "mawal",
    "category": "mobility",
    "title": "Talegaon Bridge Closure Alert",
    "summary": "A bridge between Talegaon and Dehu Road was closed for maintenance, causing local traffic diversions.",
    "timestamp": "2026-01-19T02:00:00Z",
    "expiresAt": "2026-01-25T18:30:00Z",
    "geoPoint": {
      "lat": 18.7325,
      "lng": 73.6766
    },
    "location": {
      "block": "Talegaon-Dehu Road"
    },
    "source": "Times Property",
    "verified": true,
    "meta": {
      "status": "Closed"
    }
  },
  {
    "id": "evt_MH_pune_20260102_001",
    "stateId": "MH",
    "districtId": "pune",
    "regionId": "haveli",
    "category": "infrastructure",
    "title": "Airport Infrastructure Stress Warning",
    "summary": "Authorities project 10 lakh additional flyers in 2026, leading to urgent calls for expanded space at Lohegaon Airport.",
    "timestamp": "2026-01-02T15:12:00Z",
    "expiresAt": null,
    "geoPoint": {
      "lat": 18.5822,
      "lng": 73.9197
    },
    "location": {
      "block": "Lohegaon (Pune Airport)"
    },
    "source": "The Times of India",
    "verified": true,
    "meta": {
      "projectedGrowth": "10 Lakh Flyers",
      "capacityStress": true
    }
  },
  {
    "id": "evt_DL_new_delhi_20260114_001",
    "stateId": "DL",
    "districtId": "new_delhi",
    "regionId": "new-delhi",
    "category": "weather",
    "title": "Severe Cold Wave Conditions",
    "summary": "Morning temperatures plummeted to 3°C as a severe cold wave accompanied by dense fog disrupted life at Kartavya Path.",
    "timestamp": "2026-01-14T10:35:00Z",
    "expiresAt": "2026-01-20T10:35:00Z",
    "geoPoint": {
      "lat": 28.6129,
      "lng": 77.2295
    },
    "location": {
      "block": "Kartavya Path"
    },
    "source": "The Hindu",
    "verified": true,
    "meta": {
      "minTemp": "3C"
    }
  },
  {
    "id": "evt_DL_new_delhi_20260115_001",
    "stateId": "DL",
    "districtId": "new_delhi",
    "regionId": "new-delhi",
    "category": "safety",
    "title": "Missing Persons Data Surge",
    "summary": "Police data reported 807 persons missing in the first 15 days of 2026 in New Delhi district.",
    "timestamp": "2026-01-15T18:00:00Z",
    "expiresAt": null,
    "geoPoint": {
      "lat": 28.6139,
      "lng": 77.209
    },
    "location": {
      "block": "New Delhi"
    },
    "source": "Economic Times",
    "verified": true,
    "meta": {
      "missingCount": 807
    }
  },
  {
    "id": "evt_DL_new_delhi_20260301_002",
    "stateId": "DL",
    "districtId": "new_delhi",
    "regionId": "new-delhi",
    "category": "mobility",
    "title": "Delhi Metro 394km Milestone",
    "summary": "DMRC milestone reported at Metro Bhawan, located within the New Delhi sub-division.",
    "timestamp": "2026-03-01T10:00:00Z",
    "expiresAt": null,
    "geoPoint": {
      "lat": 28.6226,
      "lng": 77.2185
    },
    "location": {
      "block": "Metro Bhawan"
    },
    "source": "India Today",
    "verified": true,
    "meta": {
      "dailyJourneys": 7000000
    }
  },
  {
    "id": "evt_DL_new_delhi_20260301_003",
    "stateId": "DL",
    "districtId": "new_delhi",
    "regionId": "new-delhi",
    "category": "safety",
    "title": "Preventable Disaster Toll Report",
    "summary": "Revenue department data for the New Delhi district revealed significant life loss due to civic lapses.",
    "timestamp": "2026-03-01T09:38:00Z",
    "expiresAt": null,
    "geoPoint": {
      "lat": 28.6139,
      "lng": 77.209
    },
    "location": {
      "block": "New Delhi"
    },
    "source": "Times of India",
    "verified": true,
    "meta": {
      "fatalities": 239
    }
  },
  {
    "id": "evt_DL_new_delhi_20260228_001",
    "stateId": "DL",
    "districtId": "new_delhi",
    "regionId": "new-delhi",
    "category": "weather",
    "title": "Above Normal Winter Heat",
    "summary": "Safdarjung observatory, located in the New Delhi sub-division, recorded markedly high temperatures.",
    "timestamp": "2026-02-28T18:00:00Z",
    "expiresAt": "2026-03-05T18:00:00Z",
    "geoPoint": {
      "lat": 28.584,
      "lng": 77.204
    },
    "location": {
      "block": "Safdarjung"
    },
    "source": "IMD",
    "verified": true,
    "meta": {
      "tempCelsius": 32.5
    }
  },
  {
    "id": "evt_DL_new_delhi_20260210_002",
    "stateId": "DL",
    "districtId": "new_delhi",
    "regionId": "new-delhi",
    "category": "emergency",
    "title": "Electric Vehicle Fire Statistics",
    "summary": "Annual safety report for New Delhi indicated a trend of 9-10 fire-related EV accidents.",
    "timestamp": "2026-02-10T11:00:00Z",
    "expiresAt": null,
    "geoPoint": {
      "lat": 28.6139,
      "lng": 77.209
    },
    "location": {
      "block": "New Delhi"
    },
    "source": "Press Information Bureau",
    "verified": true,
    "meta": {
      "evAccidents": 10454
    }
  },
  {
    "id": "evt_DL_central_20260227_001",
    "stateId": "DL",
    "districtId": "central",
    "regionId": "kotwali",
    "category": "infrastructure",
    "title": "Chandni Chowk Underground Cabling",
    "summary": "Launch of a ₹160-crore project to shift 52.5 km of overhead electricity wires underground in the historic Chandni Chowk area.",
    "timestamp": "2026-02-27T11:00:00Z",
    "expiresAt": null,
    "geoPoint": {
      "lat": 28.6506,
      "lng": 77.2304
    },
    "location": {
      "block": "Chandni Chowk"
    },
    "source": "The Times of India",
    "verified": true,
    "meta": {
      "projectCost": "160Cr"
    }
  },
  {
    "id": "evt_DL_north_west_20260301_001",
    "stateId": "DL",
    "districtId": "north_west",
    "regionId": "saraswati-vihar",
    "category": "safety",
    "title": "Community Policing Initiative Launch",
    "summary": "New community policing initiative launched in Saraswati Vihar to improve local safety and emergency response times.",
    "timestamp": "2026-03-01T14:00:00Z",
    "expiresAt": null,
    "geoPoint": {
      "lat": 28.6942,
      "lng": 77.1349
    },
    "location": {
      "block": "Saraswati Vihar"
    },
    "source": "Delhi Police",
    "verified": true,
    "meta": {
      "blocksCovered": 12
    }
  },
  {
    "id": "evt_RJ_jaipur_20260223_001",
    "stateId": "RJ",
    "districtId": "jaipur",
    "regionId": "jaipur",
    "category": "safety",
    "title": "Pedestrian Safety Walkathon Organized",
    "summary": "The Muskaan Foundation and Rajasthan Police held a walkathon to promote pedestrian-friendly infrastructure in Jaipur City Center.",
    "timestamp": "2026-02-23T03:09:00Z",
    "expiresAt": "2026-02-24T18:00:00Z",
    "geoPoint": {
      "lat": 26.9124,
      "lng": 75.7873
    },
    "location": {
      "block": "Jaipur City Center"
    },
    "source": "The Times of India",
    "verified": true,
    "meta": {
      "campaignName": "#StreetsForAll"
    }
  },
  {
    "id": "evt_PB_jalandhar_20260101_001",
    "stateId": "PB",
    "districtId": "jalandhar",
    "regionId": null,
    "category": "safety",
    "title": "National Road Safety Month",
    "summary": "State government launched a month-long awareness campaign focusing on drunk driving and over-speeding enforcement district-wide.",
    "timestamp": "2026-01-01T19:56:00Z",
    "expiresAt": "2026-01-31T23:59:00Z",
    "geoPoint": {
      "lat": 31.326,
      "lng": 75.5762
    },
    "location": {
      "block": "Jalandhar District Areas"
    },
    "source": "Babushahi.com",
    "verified": true,
    "meta": {
      "enforcementFocus": [
        "Drunk driving",
        "Wrong-side driving"
      ]
    }
  },
  {
    "id": "evt_MP_ujjain_20260215_001",
    "stateId": "MP",
    "districtId": "ujjain",
    "regionId": "ujjain-urban",
    "category": "emergency",
    "title": "Mahashivratri Crowd Management Operations",
    "summary": "Massive devotee turnout for Bhasma Aarti at Mahakaleshwar Temple required emergency crowd control and medical standby teams.",
    "timestamp": "2026-02-15T03:00:00Z",
    "expiresAt": "2026-02-16T12:00:00Z",
    "geoPoint": {
      "lat": 23.1827,
      "lng": 75.7682
    },
    "location": {
      "block": "Mahakaleshwar Temple Complex"
    },
    "source": "India TV News",
    "verified": true,
    "meta": {
      "incidentType": "Mass Gathering",
      "radiusMetres": 800
    }
  },
  {
    "id": "evt_MP_ujjain_20260123_001",
    "stateId": "MP",
    "districtId": "ujjain",
    "regionId": "tarana",
    "category": "safety",
    "title": "Communal Tensions Erupt Tarana",
    "summary": "Clashes in Tarana led to a bus being torched and shops vandalized following an attack on a local individual.",
    "timestamp": "2026-01-23T16:22:00Z",
    "expiresAt": null,
    "geoPoint": {
      "lat": 23.3333,
      "lng": 76.0167
    },
    "location": {
      "block": "Tarana Town"
    },
    "source": "India TV News",
    "verified": true,
    "meta": {
      "propertyDamage": "Bus torched"
    }
  },
  {
    "id": "evt_OD_khordha_20260224_002",
    "stateId": "OD",
    "districtId": "khordha",
    "regionId": "bhubaneswar",
    "category": "emergency",
    "title": "Billboard Collapse Kills One",
    "summary": "Gusty winds caused a large hoarding to collapse in Aiginia, killing a 38-year-old man taking shelter.",
    "timestamp": "2026-02-24T23:54:00Z",
    "expiresAt": null,
    "geoPoint": {
      "lat": 20.2641,
      "lng": 85.7812
    },
    "location": {
      "block": "Aiginia Durga Mandap"
    },
    "source": "The Times of India",
    "verified": true,
    "meta": {
      "fatalities": 1
    }
  },
  {
    "id": "evt_BR_gaya_20260224_001",
    "stateId": "BR",
    "districtId": "gaya",
    "regionId": "gaya-sadar",
    "category": "infrastructure",
    "title": "Bageshwari Overbridge Construction Starts",
    "summary": "Work commenced on a ₹90 crore railway overbridge to connect Gaya station with Ramshila.",
    "timestamp": "2026-02-24T18:45:00Z",
    "expiresAt": "2027-05-31T23:59:00Z",
    "geoPoint": {
      "lat": 24.809,
      "lng": 85.004
    },
    "location": {
      "block": "Bageshwari Railway Crossing"
    },
    "source": "The Times of India",
    "verified": true,
    "meta": {
      "projectCost": "90.16 Cr"
    }
  },
  {
    "id": "evt_UP_sitapur_20260224_001",
    "stateId": "UP",
    "districtId": "sitapur",
    "regionId": "sadar-sitapur",
    "category": "infrastructure",
    "title": "Sadar Bazar Road Expansion",
    "summary": "Authorities initiated a major road widening project in Sadar Bazar to decongest the main market area of Sitapur.",
    "timestamp": "2026-02-24T10:00:00Z",
    "expiresAt": null,
    "geoPoint": {
      "lat": 27.575,
      "lng": 80.665
    },
    "location": {
      "block": "Sadar Bazar"
    },
    "source": "Dainik Jagran",
    "verified": true,
    "meta": {
      "status": "Work in progress"
    }
  },
  {
    "id": "evt_UP_sitapur_20260223_001",
    "stateId": "UP",
    "districtId": "sitapur",
    "regionId": "sadar-sitapur",
    "category": "health",
    "title": "Mega Health Camp in Hargaon",
    "summary": "Over 500 local residents received free medical screenings and medicines during a district health department drive in Hargaon.",
    "timestamp": "2026-02-23T09:00:00Z",
    "expiresAt": "2026-02-23T18:00:00Z",
    "geoPoint": {
      "lat": 27.75,
      "lng": 80.75
    },
    "location": {
      "block": "Hargaon"
    },
    "source": "Hindustan Times",
    "verified": true,
    "meta": {
      "participants": 500
    }
  },
  {
    "id": "evt_UP_sitapur_20260220_001",
    "stateId": "UP",
    "districtId": "sitapur",
    "regionId": "misrikh",
    "category": "infrastructure",
    "title": "Canal Cleaning Drive in Machhrehta",
    "summary": "The Irrigation Department accelerated the desilting of minor canals in Machhrehta ahead of the summer crop season.",
    "timestamp": "2026-02-20T08:30:00Z",
    "expiresAt": null,
    "geoPoint": {
      "lat": 27.42,
      "lng": 80.52
    },
    "location": {
      "block": "Machhrehta"
    },
    "source": "Local Administration",
    "verified": true,
    "meta": {
      "department": "Irrigation"
    }
  },
  {
    "id": "evt_UP_sitapur_20260218_001",
    "stateId": "UP",
    "districtId": "sitapur",
    "regionId": "misrikh",
    "category": "safety",
    "title": "Solar Streetlight Installation in Atwa",
    "summary": "As part of the Gram Jyoti Yojana, 50 solar streetlights were installed in Atwa village to improve nighttime safety.",
    "timestamp": "2026-02-18T14:00:00Z",
    "expiresAt": null,
    "geoPoint": {
      "lat": 27.35,
      "lng": 80.58
    },
    "location": {
      "block": "Atwa"
    },
    "source": "Amar Ujala",
    "verified": true,
    "meta": {
      "units": 50
    }
  },
  {
    "id": "evt_UP_sitapur_20260215_001",
    "stateId": "UP",
    "districtId": "sitapur",
    "regionId": "sidhauli",
    "category": "infrastructure",
    "title": "Modern Primary School Inaugurated",
    "summary": "A new primary school with smart classroom facilities was opened in Alaudipur, benefiting 200 children.",
    "timestamp": "2026-02-15T11:00:00Z",
    "expiresAt": null,
    "geoPoint": {
      "lat": 27.28,
      "lng": 80.83
    },
    "location": {
      "block": "Alaudipur"
    },
    "source": "District Education Office",
    "verified": true,
    "meta": {
      "capacity": 200
    }
  },
  {
    "id": "evt_KA_mysuru_20260224_001",
    "stateId": "KA",
    "districtId": "mysuru",
    "regionId": "mysuru-urban",
    "category": "infrastructure",
    "title": "Hebbal Industrial Area Upgrade",
    "summary": "The Karnataka Industrial Area Development Board (KIADB) announced a ₹20 crore fund for drainage and road repairs in Hebbal.",
    "timestamp": "2026-02-24T12:00:00Z",
    "expiresAt": null,
    "geoPoint": {
      "lat": 12.358,
      "lng": 76.612
    },
    "location": {
      "block": "Hebbal"
    },
    "source": "Star of Mysore",
    "verified": true,
    "meta": {
      "funding": "20 Cr"
    }
  },
  {
    "id": "evt_KA_mysuru_20260222_001",
    "stateId": "KA",
    "districtId": "mysuru",
    "regionId": "mysuru-urban",
    "category": "safety",
    "title": "Traffic Awareness Drive in Kuvempunagar",
    "summary": "City police conducted an awareness program in Kuvempunagar to reduce accidents at major intersections.",
    "timestamp": "2026-02-22T10:00:00Z",
    "expiresAt": "2026-02-22T20:00:00Z",
    "geoPoint": {
      "lat": 12.295,
      "lng": 76.62
    },
    "location": {
      "block": "Kuvempunagar"
    },
    "source": "The Hindu",
    "verified": true,
    "meta": {
      "focus": "Helmet safety"
    }
  },
  {
    "id": "evt_KA_mysuru_20260219_001",
    "stateId": "KA",
    "districtId": "mysuru",
    "regionId": "nanjangud",
    "category": "environment",
    "title": "Kabini River Desilting Project",
    "summary": "Authorities launched a desilting drive in the Kabini River near Nanjangud to prevent flooding during the upcoming monsoon.",
    "timestamp": "2026-02-19T08:00:00Z",
    "expiresAt": null,
    "geoPoint": {
      "lat": 12.12,
      "lng": 76.68
    },
    "location": {
      "block": "Nanjangud"
    },
    "source": "Deccan Herald",
    "verified": true,
    "meta": {
      "river": "Kabini"
    }
  },
  {
    "id": "evt_KA_mysuru_20260217_001",
    "stateId": "KA",
    "districtId": "mysuru",
    "regionId": "hunsur",
    "category": "safety",
    "title": "Hunsur Forest Edge Patrols Increased",
    "summary": "Forest department intensified night patrols along the Hunsur-Nagarahole border after multiple tiger sightings reported.",
    "timestamp": "2026-02-17T21:00:00Z",
    "expiresAt": null,
    "geoPoint": {
      "lat": 12.31,
      "lng": 76.29
    },
    "location": {
      "block": "Hunsur Frontier"
    },
    "source": "Forest Department",
    "verified": true,
    "meta": {
      "threat": "Human-animal conflict"
    }
  },
  {
    "id": "evt_KA_mysuru_20260214_001",
    "stateId": "KA",
    "districtId": "mysuru",
    "regionId": "kr-nagara",
    "category": "infrastructure",
    "title": "New Bridge Over Cauvery in K.R. Nagara",
    "summary": "The state cabinet approved the construction of a new bridge across the Cauvery River connecting K.R. Nagara to Hole Narsipur.",
    "timestamp": "2026-02-14T15:30:00Z",
    "expiresAt": null,
    "geoPoint": {
      "lat": 12.45,
      "lng": 76.38
    },
    "location": {
      "block": "K.R. Nagara"
    },
    "source": "Public Works Department",
    "verified": true,
    "meta": {
      "river": "Cauvery"
    }
  },
  {
    "id": "evt_WB_hugli_20260225_001",
    "stateId": "WB",
    "districtId": "hugli",
    "regionId": null,
    "category": "emergency",
    "title": "Mild Tremors Felt District-Wide",
    "summary": "A 4.2 magnitude earthquake with epicenter in neighboring district triggered minor tremors in Chinsurah, Serampore and Singur.",
    "timestamp": "2026-02-25T03:45:00Z",
    "expiresAt": "2026-02-25T06:00:00Z",
    "geoPoint": {
      "lat": 22.9,
      "lng": 88.39
    },
    "location": {
      "block": "Hugli District Areas"
    },
    "source": "NDTV",
    "verified": true,
    "meta": {
      "magnitude": 4.2
    }
  },
  {
    "id": "evt_WB_hugli_20260223_001",
    "stateId": "WB",
    "districtId": "hugli",
    "regionId": "chinsurah",
    "category": "infrastructure",
    "title": "Hooghly Riverfront Beautification",
    "summary": "Chinsurah municipality commenced the phase 2 of riverfront development aiming to create a new promenade.",
    "timestamp": "2026-02-23T11:00:00Z",
    "expiresAt": null,
    "geoPoint": {
      "lat": 22.9,
      "lng": 88.39
    },
    "location": {
      "block": "Chinsurah Ghat"
    },
    "source": "The Statesman",
    "verified": true,
    "meta": {
      "phase": 2
    }
  },
  {
    "id": "evt_WB_hugli_20260220_001",
    "stateId": "WB",
    "districtId": "hugli",
    "regionId": "chandannagar",
    "category": "infrastructure",
    "title": "Singur Logistics Hub Construction",
    "summary": "Private developers broke ground on a massive cold storage and logistics hub near Singur on NH19.",
    "timestamp": "2026-02-20T10:30:00Z",
    "expiresAt": null,
    "geoPoint": {
      "lat": 22.82,
      "lng": 88.23
    },
    "location": {
      "block": "Singur NH19"
    },
    "source": "Business Standard",
    "verified": true,
    "meta": {
      "sector": "Logistics"
    }
  },
  {
    "id": "evt_WB_hugli_20260218_001",
    "stateId": "WB",
    "districtId": "hugli",
    "regionId": "chinsurah",
    "category": "safety",
    "title": "Bandel Imambara Restoration Security",
    "summary": "CCTV surveillance increased around the heritage site of Bandel Imambara following recent vandalism attempts.",
    "timestamp": "2026-02-18T16:00:00Z",
    "expiresAt": null,
    "geoPoint": {
      "lat": 22.91,
      "lng": 88.38
    },
    "location": {
      "block": "Bandel"
    },
    "source": "Police Bulletin",
    "verified": true,
    "meta": {
      "camCount": 16
    }
  },
  {
    "id": "evt_CT_raipur_20260224_001",
    "stateId": "CT",
    "districtId": "raipur",
    "regionId": "raipur",
    "category": "infrastructure",
    "title": "Raipur Skywalk Dismantling Reconsidered",
    "summary": "The state cabinet deferred the decision to dismantle the Raipur Skywalk, opting for a feasibility study for commercial reuse.",
    "timestamp": "2026-02-24T17:00:00Z",
    "expiresAt": null,
    "geoPoint": {
      "lat": 21.238,
      "lng": 81.634
    },
    "location": {
      "block": "Raipur City Center"
    },
    "source": "Times of India",
    "verified": true,
    "meta": {
      "infrastructureId": "SKY-01"
    }
  },
  {
    "id": "evt_CT_raipur_20260222_001",
    "stateId": "CT",
    "districtId": "raipur",
    "regionId": "naya-raipur",
    "category": "infrastructure",
    "title": "Naya Raipur Metro Neo Project",
    "summary": "The central government approved the Detailed Project Report for Metro Neo connectivity between Raipur and Naya Raipur.",
    "timestamp": "2026-02-22T13:00:00Z",
    "expiresAt": null,
    "geoPoint": {
      "lat": 21.17,
      "lng": 81.79
    },
    "location": {
      "block": "Naya Raipur Corridor"
    },
    "source": "Chhattisgarh Infotech",
    "verified": true,
    "meta": {
      "projectType": "Metro Neo"
    }
  },
  {
    "id": "evt_CT_raipur_20260219_001",
    "stateId": "CT",
    "districtId": "raipur",
    "regionId": "tilda-neora",
    "category": "infrastructure",
    "title": "Tilda Junction Modernization",
    "summary": "Upgradation work began at Tilda-Neora railway station under the Amrit Bharat Station Scheme.",
    "timestamp": "2026-02-19T09:30:00Z",
    "expiresAt": null,
    "geoPoint": {
      "lat": 21.54,
      "lng": 81.89
    },
    "location": {
      "block": "Tilda"
    },
    "source": "South Eastern Railway",
    "verified": true,
    "meta": {
      "budget": "12.5 Cr"
    }
  },
  {
    "id": "evt_TN_vellore_20260224_001",
    "stateId": "TN",
    "districtId": "vellore",
    "regionId": "vellore",
    "category": "health",
    "title": "Vellore CMC Hospital Expansion",
    "summary": "New specialty wing inaugurated at CMC Chittoor campus extension, primarily serving Vellore city patients.",
    "timestamp": "2026-02-24T10:00:00Z",
    "expiresAt": null,
    "geoPoint": {
      "lat": 12.92,
      "lng": 79.13
    },
    "location": {
      "block": "Katpadi-Sathuvachari Link"
    },
    "source": "The Hindu",
    "verified": true,
    "meta": {
      "provider": "CMC Vellore"
    }
  },
  {
    "id": "evt_TN_vellore_20260221_001",
    "stateId": "TN",
    "districtId": "vellore",
    "regionId": "vaniyambadi",
    "category": "environment",
    "title": "Palar River Bed Restoration Drive",
    "summary": "Environmentalists and district administration organized a community drive to remove illegal encroachments from the Palar river bed.",
    "timestamp": "2026-02-21T07:30:00Z",
    "expiresAt": null,
    "geoPoint": {
      "lat": 12.684,
      "lng": 78.614
    },
    "location": {
      "block": "Vaniyambadi Palar Bank"
    },
    "source": "Dinamalar",
    "verified": true,
    "meta": {
      "river": "Palar"
    }
  },
  {
    "id": "evt_TN_vellore_20260218_001",
    "stateId": "TN",
    "districtId": "vellore",
    "regionId": "gudiyatham",
    "category": "infrastructure",
    "title": "Gudiyatham Ring Road Survey",
    "summary": "Government surveyors identified land for the proposed 15km ring road to bypass Gudiyatham town congestion.",
    "timestamp": "2026-02-18T14:45:00Z",
    "expiresAt": null,
    "geoPoint": {
      "lat": 12.943,
      "lng": 78.874
    },
    "location": {
      "block": "Gudiyatham Bypass"
    },
    "source": "Local News Network",
    "verified": true,
    "meta": {
      "lengthKm": 15
    }
  }
]